[
    {
        "tw": "[羅漢島] 完成每日任務 '羅漢的修煉' 15次",
        "th": "<div class=\"d-flex justify-content-between\"><div>ลานประลองเทวาอนันต์ 30 ชั้น (รายวัน) 15 ครั้ง</div><div class=\"even-image- soul_pass_14062023_70\"></div></div>",
        "img" : "9IUykdb"
    },{
        "tw": "[千手羅漢陣] 完成每日任務 '共鳴的清晨' 15次",
        "th": "<div class=\"d-flex justify-content-between\"><div>ลานประลองอรหันต์หัตถ์เทวา (รายวัน) 15 ครั้ง</div><div class=\"even-image- soul_pass_14062023_71\"></div></div>",
        "img" : "i4j0NDM"
    },{
        "tw": "[黑蛇門隱居處] 完成每週任務 '濃濁的毒霧' 4次",
        "th": "<div class=\"d-flex justify-content-between\"><div>ที่ซ่อนกลุ่มเงามืด บอส 1 รายสัปดาห์ สะสม 4 ครั้ง</div><div class=\"even-image- soul_pass_14062023_72\"></div></div>",
        "img" : "SOxvJND"
    },{
        "tw": "[黑蛇門隱居處] 完成每週任務 '沉沒之月' 4次",
        "th": "<div class=\"d-flex justify-content-between\"><div>ที่ซ่อนกลุ่มเงามืด บอส 2 รายสัปดาห์ สะสม 4 ครั้ง</div><div class=\"even-image- soul_pass_14062023_73\"></div></div>",
        "img" : "SOxvJND"
    },{
        "tw": "[火龍的巢穴] 完成每日任務 '深淵之火' 12次",
        "th": "<div class=\"d-flex justify-content-between\"><div>มังกรไฟ 12 ครั้ง(รายวัน)</div><div class=\"even-image- soul_pass_14062023_74\"></div></div>",
        "img" : "VGb5WGV"
    },{
        "tw": "[黑龍教降臨殿] 完成每日任務 '黑龍的容器' 15次",
        "th": "<div class=\"d-flex justify-content-between\"><div>ลงดัน 黑躪教降臨肚 รายวัน 15 ครั้ง</div><div class=\"even-image- soul_pass_14062023_75\"></div></div>",
        "img" : "ejKcBna"
    },{
        "tw": "[黑龍教降臨殿] 完成斬首任務 '衝突的容器' 39次",
        "th": "<div class=\"d-flex justify-content-between\"><div>ลงดัน 黑躪教降臨肚 รายวัน 39 ครั้ง</div><div class=\"even-image- soul_pass_14062023_76\"></div></div>",
        "img" : "ejKcBna"
    },{
        "tw": "[搖風島] 完成每日任務 '鳥、風以及渾沌之島' 15次",
        "th": "<div class=\"d-flex justify-content-between\"><div>ลงดัน 搖風島(ฮาปี้) รายวัน 15 ครั้ง<</div><div class=\"even-image- soul_pass_14062023_77\"></div></div>",
        "img" : "Za97V5c"
    },{
        "tw": "[搖風島] 完成斬首任務 '猛烈颳起的黑風' 39次",
        "th": "<div class=\"d-flex justify-content-between\"><div>ลงดัน 搖風島(ฮาปี้) รายวัน 39 ครั้ง<</div><div class=\"even-image- soul_pass_14062023_78\"></div></div>",
        "img" : "Za97V5c"
    },{
        "tw": "[崑崙派本山] 完成每日任務停止的時間中 12次",
        "th": "<div class=\"d-flex justify-content-between\"><div>ลงดัน สำนักคุนลุนแห่งห้วงเวลา(คุนลุน) รายวัน 12 ครั้ง</div><div class=\"even-image- soul_pass_14062023_79\"></div></div>",
        "img" : "gjauuTg"
    },{
        "tw": "[汽南派本山] 完成每日任務停止的時間中 15次",
        "th": "<div class=\"d-flex justify-content-between\"><div>ลงดัน สำนักคุนลุนแห่งห้วงเวลา(คุนลุน) รายวัน 15 ครั้ง</div><div class=\"even-image- soul_pass_14062023_710\"></div></div>",
        "img" : "gjauuTg"
    },{
        "tw": "[渾沌黑神木] 完成每日任務 '懸吊的人' 12次",
        "th": "<div class=\"d-flex justify-content-between\"><div>ลงดัน แดนแห่งความโกลาหล รายวัน 12 ครั้ง</div><div class=\"even-image- soul_pass_14062023_711\"></div></div>",
        "img" : "Swi8Tgl"
    },{
        "tw": "[渾沌黑神木] 完成每日任務 '懸吊的人' 15次",
        "th": "<div class=\"d-flex justify-content-between\"><div>ลงดัน แดนแห่งความโกลาหล รายวัน 15 ครั้ง</div><div class=\"even-image- soul_pass_14062023_712\"></div></div>",
        "img" : "Swi8Tgl"
    },{
        "tw": "[傳承祠堂] 完成每日任務 '錯誤的繼承' 12次",
        "th": "<div class=\"d-flex justify-content-between\"><div>ลงดัน แท่นบูชาแห่งการวิวัฒนาการฝึกตน สำนักนัมโด รายวัน 12 ครั้ง</div><div class=\"even-image- soul_pass_14062023_713\"></div></div>",
        "img" : "SWkxxBb"
    },{
        "tw": "[傳承祠登] 完成每日任務 '錯誤的繼承' 15次",
        "th": "<div class=\"d-flex justify-content-between\"><div>ลงดัน แท่นบูชาแห่งการวิวัฒนาการฝึกตน สำนักนัมโด รายวัน 15 ครั้ง</div><div class=\"even-image- soul_pass_14062023_714\"></div></div>",
        "img" : "SWkxxBb"
    },{
        "tw": "[累積登入] 累積登入 15次 ",
        "th": "<div class=\"d-flex justify-content-between\"><div>ล็อกอินรายวัน สะสม 15 วัน</div><div class=\"even-image- soul_pass_14062023_715\"></div></div>",
        "img" : ""
    }
]