[
    {
        "tw": "[黑龍教變異研究所] 3段以上完成20次",
        "th": "<div class=\"d-flex justify-content-between\"><div>comingsoon</div><div class=\"even-image- soul_boost_17052023_20\"></div></div>",
        "img" : ""
    },{
        "tw": "[黑龍教變異研究所] 5段以上完成12次",
        "th": "<div class=\"d-flex justify-content-between\"><div>comingsoon</div><div class=\"even-image- soul_boost_17052023_21\"></div></div>",
        "img" : ""
    },{
        "tw": "[黑龍教降臨殿] 3段以上完成20次",
        "th": "<div class=\"d-flex justify-content-between\"><div>comingsoon</div><div class=\"even-image- soul_boost_17052023_22\"></div></div>",
        "img" : ""
    },{
        "tw": "[黑龍教降臨殿] 5段以上完成12次",
        "th": "<div class=\"d-flex justify-content-between\"><div>comingsoon</div><div class=\"even-image- soul_boost_17052023_23\"></div></div>",
        "img" : ""
    },{
        "tw": "[搖風島] 3段以上完成20次",
        "th": "<div class=\"d-flex justify-content-between\"><div>comingsoon</div><div class=\"even-image- soul_boost_17052023_24\"></div></div>",
        "img" : ""
    },{
        "tw": "[搖風島] 5段以上完成12次",
        "th": "<div class=\"d-flex justify-content-between\"><div>comingsoon</div><div class=\"even-image- soul_boost_17052023_25\"></div></div>",
        "img" : ""
    }
]